setup.py
vlinx_util.egg-info/PKG-INFO
vlinx_util.egg-info/SOURCES.txt
vlinx_util.egg-info/dependency_links.txt
vlinx_util.egg-info/top_level.txt
vlinxutil/__init__.py
vlinxutil/process_util.py