Metadata-Version: 1.0
Name: vlinx-util
Version: 0.0.5
Summary: VLINX Python Util
Home-page: https://vlinx.io/
Author: vlinx
Author-email: vlinx@vlinx.io
License: MIT
Platform: any
